test/__init__.py
test/_reader.py
test/_sample_data.py
test/_version.py
test/_widget.py
test/_writer.py
test/napari.yaml
test/_tests/__init__.py
test/_tests/test_reader.py
test/_tests/test_sample_data.py
test/_tests/test_widget.py
test/_tests/test_writer.py
test_test_test001001-0.1.dev1.dist-info/LICENSE
test_test_test001001-0.1.dev1.dist-info/METADATA
test_test_test001001-0.1.dev1.dist-info/WHEEL
test_test_test001001-0.1.dev1.dist-info/entry_points.txt
test_test_test001001-0.1.dev1.dist-info/top_level.txt
test_test_test001001-0.1.dev1.dist-info/RECORD
